artk/__init__.py
artk/answerer.py
artk/coder.py
artk/driver.py
artk/idea_generator.py
artk/main_menu.py
artk/parser.py
artk/related_papers.py
artk/rephraser.py
artk/rephraser_old.py
artk/summarizer.py
artk/transform.py
artk/utilities.py
artk/welcome_screen.py
artk-0.0.1.dist-info/LICENCE.md
artk-0.0.1.dist-info/LICENSE
artk-0.0.1.dist-info/METADATA
artk-0.0.1.dist-info/WHEEL
artk-0.0.1.dist-info/top_level.txt
artk-0.0.1.dist-info/RECORD
